{
  "@context": "https://github.com/3se-framework/3se-onto/contexts/reference.context.jsonld",
  "@type": "bibo:Book",
  "title": "Requirements Engineering Fundamentals",
  "abstract": "A Study Guide for the Certified Professional for Requirements Engineering Exam - Foundation Level - IREB compliant",
  "authorList": [
    {
      "@type": "foaf:Person",
      "name": "Klaus Pohl"
    },
    {
      "@type": "foaf:Person",
      "name": "Chris Rupp"
    }
  ],
  "status": "bibo:published",
  "date": "2015",
  "isbn13": "978-1937538835",
  "entryCreator": {
    "@type": "foaf:Person",
    "name": "@rcasteran"
  },
  "@id": "https://github.com/3se-framework/3se-onto/references/req-eng-fundamentals-2nd-ed-069a9faf2cb97eb3",
  "entryCreated": "2026-03-05",
  "entryModified": "2026-03-06"
}
